dnsblock_update/__init__.py
dnsblock_update/__main__.py
dnsblock_update/blocklist.py
dnsblock_update/config.py
dnsblock_update-0.0.2.dist-info/LICENSE
dnsblock_update-0.0.2.dist-info/METADATA
dnsblock_update-0.0.2.dist-info/WHEEL
dnsblock_update-0.0.2.dist-info/top_level.txt
dnsblock_update-0.0.2.dist-info/RECORD
