Metadata-Version: 2.1
Name: dnsblock-update
Version: 0.0.2
Summary: Blocklist Updater for DNS Masq
Home-page: https://github.com/raynigon/dnsblock-update
Author: Simon Schneider
Author-email: dev@raynigon.com
Project-URL: Bug Reports, https://github.com/raynigon/dnsblock-update/issues
Project-URL: Source, https://github.com/raynigon/dnsblock-update/
Keywords: dnsmasq
Classifier: Development Status :: 4 - Beta
Classifier: Programming Language :: Python :: 3.6
Classifier: Programming Language :: Python :: 3.7
Classifier: Programming Language :: Python :: 3.8
Classifier: Programming Language :: Python :: 3.9
Classifier: License :: OSI Approved :: Apache Software License
Classifier: Operating System :: OS Independent
Requires-Python: >=3.6, <4
License-File: LICENSE
Requires-Dist: requests
Requires-Dist: pyyaml
Provides-Extra: dev
Requires-Dist: setuptools ; extra == 'dev'
Requires-Dist: wheel ; extra == 'dev'
Provides-Extra: test
Requires-Dist: coverage ; extra == 'test'
